pyiron_workflow/__init__.py
pyiron_workflow/_tests.py
pyiron_workflow/_version.py
pyiron_workflow/api.py
pyiron_workflow/channels.py
pyiron_workflow/create.py
pyiron_workflow/data.py
pyiron_workflow/draw.py
pyiron_workflow/find.py
pyiron_workflow/identifier.py
pyiron_workflow/io.py
pyiron_workflow/knowledge.py
pyiron_workflow/logging.py
pyiron_workflow/node.py
pyiron_workflow/output_parser.py
pyiron_workflow/overloading.py
pyiron_workflow/storage.py
pyiron_workflow/suggest.py
pyiron_workflow/topology.py
pyiron_workflow/type_hinting.py
pyiron_workflow/workflow.py
pyiron_workflow/executors/README.md
pyiron_workflow/executors/__init__.py
pyiron_workflow/executors/cloudpickleprocesspool.py
pyiron_workflow/executors/wrapped_executorlib.py
pyiron_workflow/mixin/__init__.py
pyiron_workflow/mixin/display_state.py
pyiron_workflow/mixin/has_interface_mixins.py
pyiron_workflow/mixin/injection.py
pyiron_workflow/mixin/lexical.py
pyiron_workflow/mixin/preview.py
pyiron_workflow/mixin/run.py
pyiron_workflow/nodes/__init__.py
pyiron_workflow/nodes/composite.py
pyiron_workflow/nodes/for_loop.py
pyiron_workflow/nodes/function.py
pyiron_workflow/nodes/macro.py
pyiron_workflow/nodes/multiple_distpatch.py
pyiron_workflow/nodes/standard.py
pyiron_workflow/nodes/static_io.py
pyiron_workflow/nodes/transform.py
pyiron_workflow/nodes/while_loop.py
pyiron_workflow-0.15.4.dist-info/METADATA
pyiron_workflow-0.15.4.dist-info/WHEEL
pyiron_workflow-0.15.4.dist-info/licenses/LICENSE
pyiron_workflow-0.15.4.dist-info/RECORD
