Metadata-Version: 2.4
Name: pyiron_workflow
Version: 0.15.4
Summary: pyiron_workflow - Graph-and-node based workflow tools.
Project-URL: Homepage, https://github.com/pyiron/pyiron_workflow
Project-URL: Documentation, https://pyiron-workflow.readthedocs.io
Project-URL: Repository, https://github.com/pyiron/pyiron_workflow
Author-email: Liam Huber <liamhuber@greyhavensolutions.com>
License: BSD 3-Clause License
License-File: LICENSE
Keywords: pyiron
Classifier: Development Status :: 4 - Beta
Classifier: Intended Audience :: Science/Research
Classifier: License :: OSI Approved :: BSD License
Classifier: Operating System :: OS Independent
Classifier: Programming Language :: Python :: 3.11
Classifier: Programming Language :: Python :: 3.12
Classifier: Programming Language :: Python :: 3.13
Classifier: Topic :: Scientific/Engineering
Requires-Python: <3.14,>=3.11
Requires-Dist: bagofholding<=0.1.5,>=0.1.0
Requires-Dist: bidict==0.23.1
Requires-Dist: cloudpickle<3.2.0,>=3.0.0
Requires-Dist: executorlib<1.8.0,>=1.5.3
Requires-Dist: graphviz<=0.21,>=0.20.3
Requires-Dist: pandas<2.4.0,>=2.2.2
Requires-Dist: pint<=0.25,>=0.24
Requires-Dist: pyiron-snippets<2.0.0,>=0.1.4
Requires-Dist: rdflib<7.2.0,>=7.1.4
Requires-Dist: semantikon==0.0.22
Requires-Dist: toposort==1.10
Requires-Dist: typeguard<4.5.0,>=4.2.0
Provides-Extra: cluster
Requires-Dist: h5py==3.14.0; extra == 'cluster'
Requires-Dist: pysqa==0.3.2; extra == 'cluster'
